zll/README.md
zll/__init__.py
zll/hosts.csv
zll/zll.py
zll-0.1.11.dist-info/METADATA
zll-0.1.11.dist-info/WHEEL
zll-0.1.11.dist-info/entry_points.txt
zll-0.1.11.dist-info/RECORD
