Metadata-Version: 2.1
Name: zll
Version: 0.1.11
Summary: my ssh client
Home-page: https://github.com/bigzhu/zll
Keywords: ssh,tool
Author: bigzhu
Author-email: vermiliondun@gmail.com
Requires-Python: >=3.10,<4.0
Classifier: Programming Language :: Python :: 3
Classifier: Programming Language :: Python :: 3.10
Classifier: Programming Language :: Python :: 3.11
Classifier: Programming Language :: Python :: 3.12
Requires-Dist: appdirs (>=1.4.4,<2.0.0)
Requires-Dist: zbig (>=0.1.20,<0.2.0)
Project-URL: Documentation, https://github.com/bigzhu/zll
Project-URL: Repository, https://github.com/bigzhu/zll
